{
    "stages": {
        "1": {
            "comment": "", 
            "tasks": {
                "1": {
                    "isShowByProgressbar": 0, 
                    "title": "复活陆压", 
                    "reqVal": 1, 
                    "priority": 0, 
                    "param3": "", 
                    "param2": "", 
                    "param1": "", 
                    "type": "SStageTask_CustomTask", 
                    "navigateData": "20012683#L_ZXG_Planes001"
                }
            }, 
            "title": "复活陆压"
        }
    }, 
    "describe": "", 
    "beginOnSpaceInit": 1, 
    "name": "复活陆压"
}