{
    "20101110": {
        "tasks": [
            {
                "navigateData": "10000080#L_KLZ", 
                "goal": 1, 
                "TaskClass": "QuestTaskGetTo", 
                "priority": 0, 
                "param3": "15", 
                "param2": "-207797 -207064 19059.462891", 
                "param1": "L_KLZ", 
                "id": 1, 
                "name": "回禀师尊"
            }
        ], 
        "acceptedFunctions": [
            {
                "script": "QuestFuncUseSkill", 
                "param5": "", 
                "param4": "", 
                "param3": "", 
                "param2": "", 
                "param1": "110000068"
            }
        ], 
        "unFinishTaskDes": "", 
        "id": 20101110, 
        "isAutoQuest": 1, 
        "committedFunctions": [], 
        "requirements": [
            {
                "script": "QuestRequirementCamp", 
                "param5": "", 
                "param4": "", 
                "param3": "", 
                "param2": "", 
                "param1": "1"
            }, 
            {
                "script": "QuestRequirementMissionCompleted", 
                "param5": "", 
                "param4": "", 
                "param3": "", 
                "param2": "", 
                "param1": "20101109"
            }, 
            {
                "script": "QuestRequirementProfession", 
                "param5": "", 
                "param4": "", 
                "param3": "", 
                "param2": "", 
                "param1": "1"
            }
        ], 
        "script": "QuestScriptMainline", 
        "canShare": 0, 
        "abandonFunctions": [], 
        "QuestClass": "QuestNormal", 
        "rewards": [
            {
                "param2": "", 
                "param3": "", 
                "description": "", 
                "param1": "2068", 
                "script": "QuestRewardExp"
            }, 
            {
                "param2": "", 
                "param3": "", 
                "description": "", 
                "param1": "509", 
                "script": "QuestRewardPotential"
            }, 
            {
                "param2": "", 
                "param3": "", 
                "description": "", 
                "param1": "827", 
                "script": "QuestRewardXiuwei"
            }, 
            {
                "param2": "", 
                "param3": "", 
                "description": "", 
                "param1": "474", 
                "script": "QuestRewardMoney"
            }, 
            {
                "param2": "", 
                "param3": "", 
                "description": "", 
                "param1": "1", 
                "script": "QuestRewardTitle"
            }
        ], 
        "description": "Q020138|Q020139|Q020141", 
        "finish_by": "", 
        "taskLogDes": "@S{4}在浮黎真人的帮助下你成功觉醒了盘古血脉，成为了盘古大神的传承者，请速返回昆仑宗回禀师尊。", 
        "canAbandon": 1, 
        "taskCompleteRewards": {}, 
        "finishTaskDes": "", 
        "nextQuest": "20101112", 
        "taskCompleteFunctions": {
            "1": [
                {
                    "script": "QuestFuncUseSkill", 
                    "param5": "", 
                    "param4": "", 
                    "param3": "", 
                    "param2": "", 
                    "param1": "110000282"
                }, 
                {
                    "script": "QuestFuncSetTeleportPointClose", 
                    "param5": "", 
                    "param4": "", 
                    "param3": "", 
                    "param2": "", 
                    "param1": "2019|2020"
                }
            ]
        }, 
        "level": 15, 
        "title": "盘古血脉觉醒", 
        "isAutoCommit": 1, 
        "start_by": "10000060#L_SGMJ", 
        "isAutoAccept": 1
    }
}